{
  "game_id": "2021039133",
  "collected_at": "2026-07-15T01:03:55.372842+09:00",
  "atbat_count": 17,
  "pitch_count": 44,
  "atbats": [
    {
      "index": "0110100",
      "inning": 1,
      "top_bottom": "表",
      "result_summary": "三ゴロ",
      "result_detail": "フォーク",
      "pitch_count": 6,
      "pitches": [
        {
          "no": 1,
          "type": "ワンシーム",
          "speed_kmh": 147,
          "result": "ファウル",
          "course": {
            "top_px": 31.68,
            "left_px": 13.32,
            "grid_row": 2,
            "grid_col": 1,
            "label": "真ん中・外"
          }
        },
        {
          "no": 2,
          "type": "スライダー",
          "speed_kmh": 133,
          "result": "見逃し",
          "course": {
            "top_px": 33.839999999999996,
            "left_px": 31.32,
            "grid_row": 2,
            "grid_col": 2,
            "label": "真ん中・真ん中"
          }
        },
        {
          "no": 3,
          "type": "スライダー",
          "speed_kmh": 134,
          "result": "ファウル",
          "course": {
            "top_px": 24.84,
            "left_px": 43.199999999999996,
            "grid_row": 1,
            "grid_col": 3,
            "label": "高め・内"
          }
        },
        {
          "no": 4,
          "type": "フォーク",
          "speed_kmh": 128,
          "result": "ファウル",
          "course": {
            "top_px": 50.76,
            "left_px": 5.3999999999999995,
            "grid_row": 4,
            "grid_col": 0,
            "label": "低め・外"
          }
        },
        {
          "no": 5,
          "type": "ストレート",
          "speed_kmh": 151,
          "result": "ボール",
          "course": {
            "top_px": 34.56,
            "left_px": 6.12,
            "grid_row": 2,
            "grid_col": 0,
            "label": "真ん中・外"
          }
        },
        {
          "no": 6,
          "type": "フォーク",
          "speed_kmh": null,
          "result": "三ゴロ",
          "course": {
            "top_px": 53.64,
            "left_px": 15.479999999999999,
            "grid_row": 4,
            "grid_col": 1,
            "label": "低め・外"
          }
        }
      ]
    },
    {
      "index": "0120100",
      "inning": 1,
      "top_bottom": "裏",
      "result_summary": "中フライ",
      "result_detail": "フォーク",
      "pitch_count": 3,
      "pitches": [
        {
          "no": 1,
          "type": "ストレート",
          "speed_kmh": 150,
          "result": "ファウル",
          "course": {
            "top_px": 20.88,
            "left_px": 33.839999999999996,
            "grid_row": 1,
            "grid_col": 2,
            "label": "高め・真ん中"
          }
        },
        {
          "no": 2,
          "type": "フォーク",
          "speed_kmh": 146,
          "result": "ボール[ワンバウンド]",
          "course": {
            "top_px": 58.68,
            "left_px": 36.72,
            "grid_row": 4,
            "grid_col": 2,
            "label": "低め・真ん中"
          }
        },
        {
          "no": 3,
          "type": "フォーク",
          "speed_kmh": null,
          "result": "中飛",
          "course": {
            "top_px": 42.839999999999996,
            "left_px": 33.12,
            "grid_row": 3,
            "grid_col": 2,
            "label": "低め・真ん中"
          }
        }
      ]
    },
    {
      "index": "0210100",
      "inning": 2,
      "top_bottom": "表",
      "result_summary": "右フライ",
      "result_detail": "フォーク",
      "pitch_count": 5,
      "pitches": [
        {
          "no": 1,
          "type": "ワンシーム",
          "speed_kmh": 143,
          "result": "見逃し",
          "course": {
            "top_px": 17.28,
            "left_px": 13.32,
            "grid_row": 1,
            "grid_col": 1,
            "label": "高め・外"
          }
        },
        {
          "no": 2,
          "type": "ストレート",
          "speed_kmh": 148,
          "result": "ボール",
          "course": {
            "top_px": 9.0,
            "left_px": 6.4799999999999995,
            "grid_row": 0,
            "grid_col": 0,
            "label": "高め・外"
          }
        },
        {
          "no": 3,
          "type": "ワンシーム",
          "speed_kmh": 147,
          "result": "見逃し",
          "course": {
            "top_px": 39.24,
            "left_px": 11.879999999999999,
            "grid_row": 3,
            "grid_col": 0,
            "label": "低め・外"
          }
        },
        {
          "no": 4,
          "type": "フォーク",
          "speed_kmh": 129,
          "result": "ファウル",
          "course": {
            "top_px": 39.96,
            "left_px": 6.4799999999999995,
            "grid_row": 3,
            "grid_col": 0,
            "label": "低め・外"
          }
        },
        {
          "no": 5,
          "type": "フォーク",
          "speed_kmh": null,
          "result": "右飛",
          "course": {
            "top_px": 54.0,
            "left_px": 22.32,
            "grid_row": 4,
            "grid_col": 1,
            "label": "低め・外"
          }
        }
      ]
    },
    {
      "index": "0220100",
      "inning": 2,
      "top_bottom": "裏",
      "result_summary": "遊ゴロ",
      "result_detail": "フォーク",
      "pitch_count": 2,
      "pitches": [
        {
          "no": 1,
          "type": "カットボール",
          "speed_kmh": 137,
          "result": "空振り",
          "course": {
            "top_px": 35.64,
            "left_px": 6.84,
            "grid_row": 2,
            "grid_col": 0,
            "label": "真ん中・外"
          }
        },
        {
          "no": 2,
          "type": "フォーク",
          "speed_kmh": null,
          "result": "遊ゴロ",
          "course": {
            "top_px": 19.08,
            "left_px": 37.44,
            "grid_row": 1,
            "grid_col": 2,
            "label": "高め・真ん中"
          }
        }
      ]
    },
    {
      "index": "0310100",
      "inning": 3,
      "top_bottom": "表",
      "result_summary": "空振り三振",
      "result_detail": "フォーク、ワンバウンド",
      "pitch_count": 3,
      "pitches": [
        {
          "no": 1,
          "type": "スライダー",
          "speed_kmh": 134,
          "result": "空振り",
          "course": {
            "top_px": 22.32,
            "left_px": 35.64,
            "grid_row": 1,
            "grid_col": 2,
            "label": "高め・真ん中"
          }
        },
        {
          "no": 2,
          "type": "スライダー",
          "speed_kmh": 134,
          "result": "空振り",
          "course": {
            "top_px": 40.32,
            "left_px": 43.92,
            "grid_row": 3,
            "grid_col": 3,
            "label": "低め・内"
          }
        },
        {
          "no": 3,
          "type": "フォーク",
          "speed_kmh": null,
          "result": "空三振[ワンバウンド]",
          "course": {
            "top_px": 57.96,
            "left_px": 9.719999999999999,
            "grid_row": 4,
            "grid_col": 0,
            "label": "低め・外"
          }
        }
      ]
    },
    {
      "index": "0320100",
      "inning": 3,
      "top_bottom": "裏",
      "result_summary": "空振り三振",
      "result_detail": "ストレート",
      "pitch_count": 8,
      "pitches": [
        {
          "no": 1,
          "type": "スライダー",
          "speed_kmh": 129,
          "result": "見逃し",
          "course": {
            "top_px": 43.559999999999995,
            "left_px": 37.44,
            "grid_row": 3,
            "grid_col": 2,
            "label": "低め・真ん中"
          }
        },
        {
          "no": 2,
          "type": "フォーク",
          "speed_kmh": 146,
          "result": "ボール[ワンバウンド]",
          "course": {
            "top_px": 59.4,
            "left_px": 28.439999999999998,
            "grid_row": 4,
            "grid_col": 2,
            "label": "低め・真ん中"
          }
        },
        {
          "no": 3,
          "type": "カットボール",
          "speed_kmh": 137,
          "result": "ファウル",
          "course": {
            "top_px": 21.24,
            "left_px": 13.32,
            "grid_row": 1,
            "grid_col": 1,
            "label": "高め・外"
          }
        },
        {
          "no": 4,
          "type": "シュート",
          "speed_kmh": 148,
          "result": "ファウル",
          "course": {
            "top_px": 9.719999999999999,
            "left_px": 23.4,
            "grid_row": 0,
            "grid_col": 1,
            "label": "高め・外"
          }
        },
        {
          "no": 5,
          "type": "シュート",
          "speed_kmh": 151,
          "result": "ボール",
          "course": {
            "top_px": 29.16,
            "left_px": 5.76,
            "grid_row": 2,
            "grid_col": 0,
            "label": "真ん中・外"
          }
        },
        {
          "no": 6,
          "type": "フォーク",
          "speed_kmh": 146,
          "result": "ボール[ワンバウンド]",
          "course": {
            "top_px": 60.48,
            "left_px": 40.32,
            "grid_row": 4,
            "grid_col": 3,
            "label": "低め・内"
          }
        },
        {
          "no": 7,
          "type": "ストレート",
          "speed_kmh": 153,
          "result": "ファウル",
          "course": {
            "top_px": 7.199999999999999,
            "left_px": 14.04,
            "grid_row": 0,
            "grid_col": 1,
            "label": "高め・外"
          }
        },
        {
          "no": 8,
          "type": "ストレート",
          "speed_kmh": null,
          "result": "空三振",
          "course": {
            "top_px": 7.199999999999999,
            "left_px": 43.199999999999996,
            "grid_row": 0,
            "grid_col": 3,
            "label": "高め・内"
          }
        }
      ]
    },
    {
      "index": "0410100",
      "inning": 4,
      "top_bottom": "表",
      "result_summary": "四球",
      "result_detail": "ストレート、セーフティバント、バント構え、ランナー1塁",
      "pitch_count": 4,
      "pitches": [
        {
          "no": 1,
          "type": "ストレート",
          "speed_kmh": 146,
          "result": "ボール",
          "course": {
            "top_px": 56.16,
            "left_px": 44.64,
            "grid_row": 4,
            "grid_col": 3,
            "label": "低め・内"
          }
        },
        {
          "no": 2,
          "type": "スライダー",
          "speed_kmh": 133,
          "result": "ボール",
          "course": {
            "top_px": 54.36,
            "left_px": 43.199999999999996,
            "grid_row": 4,
            "grid_col": 3,
            "label": "低め・内"
          }
        },
        {
          "no": 3,
          "type": "スライダー",
          "speed_kmh": 133,
          "result": "ボール",
          "course": {
            "top_px": 58.32,
            "left_px": 42.839999999999996,
            "grid_row": 4,
            "grid_col": 3,
            "label": "低め・内"
          }
        },
        {
          "no": 4,
          "type": "ストレート",
          "speed_kmh": null,
          "result": "四球[セーフティバント、バント構え]",
          "course": {
            "top_px": 56.16,
            "left_px": 46.08,
            "grid_row": 4,
            "grid_col": 3,
            "label": "低め・内"
          }
        }
      ]
    },
    {
      "index": "0420100",
      "inning": 4,
      "top_bottom": "裏",
      "result_summary": "右フライ",
      "result_detail": "カットボール",
      "pitch_count": 1,
      "pitches": [
        {
          "no": 1,
          "type": "カットボール",
          "speed_kmh": null,
          "result": "右飛",
          "course": {
            "top_px": 21.24,
            "left_px": 14.04,
            "grid_row": 1,
            "grid_col": 1,
            "label": "高め・外"
          }
        }
      ]
    },
    {
      "index": "0510100",
      "inning": 5,
      "top_bottom": "表",
      "result_summary": "空振り三振",
      "result_detail": "ワンシーム",
      "pitch_count": 4,
      "pitches": [
        {
          "no": 1,
          "type": "ワンシーム",
          "speed_kmh": 146,
          "result": "見逃し",
          "course": {
            "top_px": 44.64,
            "left_px": 33.839999999999996,
            "grid_row": 3,
            "grid_col": 2,
            "label": "低め・真ん中"
          }
        },
        {
          "no": 2,
          "type": "ワンシーム",
          "speed_kmh": 147,
          "result": "ファウル",
          "course": {
            "top_px": 30.24,
            "left_px": 23.4,
            "grid_row": 2,
            "grid_col": 1,
            "label": "真ん中・外"
          }
        },
        {
          "no": 3,
          "type": "ストレート",
          "speed_kmh": 149,
          "result": "ボール",
          "course": {
            "top_px": 32.76,
            "left_px": 6.4799999999999995,
            "grid_row": 2,
            "grid_col": 0,
            "label": "真ん中・外"
          }
        },
        {
          "no": 4,
          "type": "ワンシーム",
          "speed_kmh": null,
          "result": "空三振",
          "course": {
            "top_px": 19.8,
            "left_px": 6.4799999999999995,
            "grid_row": 1,
            "grid_col": 0,
            "label": "高め・外"
          }
        }
      ]
    },
    {
      "index": "0520100",
      "inning": 5,
      "top_bottom": "裏",
      "result_summary": "二ゴロ",
      "result_detail": "スライダー、当てただけ、バットの先",
      "pitch_count": 4,
      "pitches": [
        {
          "no": 1,
          "type": "カットボール",
          "speed_kmh": 135,
          "result": "ファウル",
          "course": {
            "top_px": 32.04,
            "left_px": 23.4,
            "grid_row": 2,
            "grid_col": 1,
            "label": "真ん中・外"
          }
        },
        {
          "no": 2,
          "type": "ストレート",
          "speed_kmh": 147,
          "result": "ボール",
          "course": {
            "top_px": 54.0,
            "left_px": 7.199999999999999,
            "grid_row": 4,
            "grid_col": 0,
            "label": "低め・外"
          }
        },
        {
          "no": 3,
          "type": "カットボール",
          "speed_kmh": 134,
          "result": "ファウル[クイック投法]",
          "course": {
            "top_px": 14.399999999999999,
            "left_px": 27.72,
            "grid_row": 1,
            "grid_col": 2,
            "label": "高め・真ん中"
          }
        },
        {
          "no": 4,
          "type": "スライダー",
          "speed_kmh": null,
          "result": "二ゴロ[当てただけ、バットの先]",
          "course": {
            "top_px": 43.559999999999995,
            "left_px": 5.76,
            "grid_row": 3,
            "grid_col": 0,
            "label": "低め・外"
          }
        }
      ]
    },
    {
      "index": "0610100",
      "inning": 6,
      "top_bottom": "表",
      "result_summary": "見逃し三振",
      "result_detail": "ストレート",
      "pitch_count": 3,
      "pitches": [
        {
          "no": 1,
          "type": "ストレート",
          "speed_kmh": 143,
          "result": "見逃し",
          "course": {
            "top_px": 44.64,
            "left_px": 37.44,
            "grid_row": 3,
            "grid_col": 2,
            "label": "低め・真ん中"
          }
        },
        {
          "no": 2,
          "type": "ストレート",
          "speed_kmh": 144,
          "result": "見逃し",
          "course": {
            "top_px": 40.68,
            "left_px": 31.68,
            "grid_row": 3,
            "grid_col": 2,
            "label": "低め・真ん中"
          }
        },
        {
          "no": 3,
          "type": "ストレート",
          "speed_kmh": null,
          "result": "見三振",
          "course": {
            "top_px": 20.16,
            "left_px": 38.879999999999995,
            "grid_row": 1,
            "grid_col": 3,
            "label": "高め・内"
          }
        }
      ]
    },
    {
      "index": "0620100",
      "inning": 6,
      "top_bottom": "裏",
      "result_summary": "右安打",
      "result_detail": "スライダー、ランナー1塁",
      "pitch_count": 1,
      "pitches": [
        {
          "no": 1,
          "type": "スライダー",
          "speed_kmh": null,
          "result": "右安",
          "course": {
            "top_px": 52.919999999999995,
            "left_px": 23.4,
            "grid_row": 4,
            "grid_col": 1,
            "label": "低め・外"
          }
        }
      ]
    },
    {
      "index": "0710000",
      "inning": 7,
      "top_bottom": "表",
      "result_summary": "【守備】赤羽：（三）→（一）、松下：（走）→（三）",
      "result_detail": null,
      "pitch_count": 0,
      "pitches": []
    },
    {
      "index": "0720000",
      "inning": 7,
      "top_bottom": "裏",
      "result_summary": "【継投】泉→中川、【守備】坂本勇：（打）→（三）",
      "result_detail": "【今季】試26 防1.69 2勝0敗10H0S",
      "pitch_count": 0,
      "pitches": []
    },
    {
      "index": "0810000",
      "inning": 8,
      "top_bottom": "表",
      "result_summary": "【継投】山野→清水、【守備】（右）塩見、モンテル：（走）→（中）、岩田：（中）→（左）",
      "result_detail": "【今季】試25 防1.23 1勝0敗10H1S",
      "pitch_count": 0,
      "pitches": []
    },
    {
      "index": "0820000",
      "inning": 8,
      "top_bottom": "裏",
      "result_summary": "【継投】船迫→堀田、【守備】（二）門脇",
      "result_detail": "【今季】試14 防0.51 1勝0敗0H0S",
      "pitch_count": 0,
      "pitches": []
    },
    {
      "index": "0910000",
      "inning": 9,
      "top_bottom": "表",
      "result_summary": "【継投】清水→キハダ",
      "result_detail": "【今季】試31 防2.83 2勝4敗1H20S",
      "pitch_count": 0,
      "pitches": []
    }
  ]
}